HTSplotter/__init__.py
HTSplotter/arrayRGB.py
HTSplotter/categorisation.py
HTSplotter/combination.py
HTSplotter/commonfunctions.py
HTSplotter/compoundscreen.py
HTSplotter/doseresponse.py
HTSplotter/doseresponsecurvefunctionscommon.py
HTSplotter/doseresponseplots.py
HTSplotter/filenames.py
HTSplotter/geneticchemicalperturbagem.py
HTSplotter/geneticperturbagem.py
HTSplotter/growthrate.py
HTSplotter/grupping.py
HTSplotter/hdf5functions.py
HTSplotter/headers.py
HTSplotter/interactionsuser.py
HTSplotter/main.py
HTSplotter/plotting.py
HTSplotter/readfiles.py
HTSplotter/save_hdf5brfiles.py
HTSplotter/save_hdf5file.py
HTSplotter/synergism.py
HTSplotter/synergyprocessing.py
HTSplotter/timepointselection.py
HTSplotter/txtsavedata.py
HTSplotter/web.py
HTSplotter-2.11.dist-info/LICENSE.md
HTSplotter-2.11.dist-info/LICENSE.txt
HTSplotter-2.11.dist-info/METADATA
HTSplotter-2.11.dist-info/WHEEL
HTSplotter-2.11.dist-info/top_level.txt
HTSplotter-2.11.dist-info/RECORD
