Metadata-Version: 2.1
Name: HTSplotter
Version: 2.11
Summary: An end-to-end data processing, analysis and visualisation tool for chemical and genetic in vitro perturbation screens
Home-page: https://github.com/CBIGR/HTSplotter
Author: CarolinadCNunes
Author-email: carolina.decarvalhonunes@ugent.be
License: GNU General Public License v3 or later (GPLv3+)
Download-URL: https://github.com/CBIGR/HTSplotter/archive/refs/tags/HTSplotter_v0.15.tar.gz
Keywords: High-throughput screening,drug combination,genetic-chemical perturbation,dose-response,HTS,Bliss,synergism,antagonism
Platform: UNKNOWN
Classifier: Development Status :: 4 - Beta
Classifier: Intended Audience :: Developers
Classifier: Topic :: Software Development :: Build Tools
Classifier: License :: OSI Approved :: GNU General Public License v3 or later (GPLv3+)
Classifier: Programming Language :: Python :: 3
Classifier: Programming Language :: Python :: 3.4
Classifier: Programming Language :: Python :: 3.5
Classifier: Programming Language :: Python :: 3.6
Classifier: Programming Language :: Python :: 3.7
Classifier: Programming Language :: Python :: 3.8
Classifier: Programming Language :: Python :: 3.9
Requires-Dist: certifi
Requires-Dist: cycler
Requires-Dist: h5py
Requires-Dist: kiwisolver
Requires-Dist: matplotlib
Requires-Dist: minio
Requires-Dist: numpy
Requires-Dist: pandas
Requires-Dist: Pillow
Requires-Dist: psutil
Requires-Dist: pyparsing
Requires-Dist: pyPdf
Requires-Dist: PyPDF2
Requires-Dist: PyPDF3
Requires-Dist: python-dateutil
Requires-Dist: pytz
Requires-Dist: scipy
Requires-Dist: seaborn
Requires-Dist: six
Requires-Dist: tqdm
Requires-Dist: urllib3
Requires-Dist: xlrd
